README.md
setup.py
slimleaf/__init__.py
slimleaf/exceptions.py
slimleaf.egg-info/PKG-INFO
slimleaf.egg-info/SOURCES.txt
slimleaf.egg-info/dependency_links.txt
slimleaf.egg-info/requires.txt
slimleaf.egg-info/top_level.txt
slimleaf/pages/__init__.py
slimleaf/pages/element.py
slimleaf/pages/page.py
slimleaf/pages/mobile/__init__.py
slimleaf/pages/mobile/elements.py
slimleaf/pages/mobile/mobile_page.py
slimleaf/pages/web/__init__.py
slimleaf/pages/web/web_page.py
slimleaf/utils/__init__.py
slimleaf/utils/utils.py
slimleaf/webdriver/__init__.py
slimleaf/webdriver/custom_waits.py
slimleaf/webdriver/exceptions.py
slimleaf/webdriver/locator.py
tests/__init__.py
tests/conftest.py
tests/pages/__init__.py
tests/pages/test_elements.py
tests/pages/test_page.py
tests/pages/web/__init__.py
tests/pages/web/test_elements.py
tests/pages/web/test_web_page.py