Metadata-Version: 1.0
Name: slimleaf
Version: 1.0.9
Summary: A sensible approach to fast, scalable, robust UI automation suites in Python
Home-page: https://github.com/brandonblair/slimleaf
Author: Brandon Blair
Author-email: cbrandon.blair@gmail.com
License: UNKNOWN
Platform: UNKNOWN
